MANIFEST.in
README.md
setup.py
py_stresser.egg-info/PKG-INFO
py_stresser.egg-info/SOURCES.txt
py_stresser.egg-info/dependency_links.txt
py_stresser.egg-info/entry_points.txt
py_stresser.egg-info/top_level.txt
stresser/__init__.py
stresser/__main__.py
stresser/modules/__init__.py
stresser/modules/checker.py
stresser/modules/launch.py
stresser/modules/parse.py